composio_crewai/__init__.py
composio_crewai/providers.py
composio_crewai/py.typed
composio_crewai-0.10.7.dist-info/METADATA
composio_crewai-0.10.7.dist-info/WHEEL
composio_crewai-0.10.7.dist-info/top_level.txt
composio_crewai-0.10.7.dist-info/RECORD
